{
    "pagina": 514,
    "segmentos": [
        {
            "tokens": [
                0,
                14159,
                139,
                1890,
                2684,
                263,
                47531,
                757,
                4843,
                366,
                29781,
                6528,
                1879,
                366,
                44,
                48,
                14740,
                5383,
                2076,
                13449,
                26747,
                7744,
                2118,
                16286,
                5885,
                41623,
                2620,
                5382,
                673,
                5885,
                226,
                2620,
                3813,
                32448,
                1864,
                9162,
                113,
                155,
                12938,
                6,
                3414,
                12938,
                6,
                466,
                12938,
                12936,
                13732,
                8041,
                15421,
                42740,
                2371,
                7744,
                1723,
                221,
                19142,
                17678,
                36352,
                1723,
                673,
                5885,
                27148,
                1721,
                15953,
                4903,
                139,
                26883,
                504,
                73,
                3387,
                73,
                14517,
                5089,
                43602,
                17045,
                2562,
                7744,
                5885,
                226,
                2336,
                12928,
                6372,
                2688,
                2606,
                1723,
                5885,
                12238,
                15513,
                28737,
                18335,
                2076,
                2889,
                854,
                18335,
                2076,
                2889,
                28761,
                1723,
                1889,
                2118,
                2
            ],
            "texto_original": " Texto Unico de Procedimientos Administrativos “GOBIERNO REGIONAL DEL DEPARTAMENTO DE LAMBAYEQUE\" 3°,49°,9° ESTABLECE DISPOSICIONES PARA EL PROCESO DE __ |Decreto Ley 18/04/2012 FORMALIZACION DE LAS ACTIVIDADES DE PEQUENA MINERIA Y MINERIA ARTESANAL",
            "coordenadas": [
                [
                    0,
                    0,
                    0,
                    0
                ],
                [
                    361,
                    62,
                    396,
                    68
                ],
                [
                    361,
                    62,
                    396,
                    68
                ],
                [
                    401,
                    60,
                    437,
                    68
                ],
                [
                    401,
                    60,
                    437,
                    68
                ],
                [
                    442,
                    61,
                    456,
                    68
                ],
                [
                    462,
                    61,
                    561,
                    68
                ],
                [
                    462,
                    61,
                    561,
                    68
                ],
                [
                    462,
                    61,
                    561,
                    68
                ],
                [
                    462,
                    61,
                    561,
                    68
                ],
                [
                    566,
                    61,
                    666,
                    68
                ],
                [
                    566,
                    61,
                    666,
                    68
                ],
                [
                    566,
                    61,
                    666,
                    68
                ],
                [
                    566,
                    61,
                    666,
                    68
                ],
                [
                    300,
                    76,
                    378,
                    82
                ],
                [
                    300,
                    76,
                    378,
                    82
                ],
                [
                    300,
                    76,
                    378,
                    82
                ],
                [
                    300,
                    76,
                    378,
                    82
                ],
                [
                    300,
                    76,
                    378,
                    82
                ],
                [
                    300,
                    76,
                    378,
                    82
                ],
                [
                    382,
                    76,
                    453,
                    82
                ],
                [
                    382,
                    76,
                    453,
                    82
                ],
                [
                    382,
                    76,
                    453,
                    82
                ],
                [
                    457,
                    76,
                    483,
                    82
                ],
                [
                    488,
                    76,
                    600,
                    82
                ],
                [
                    488,
                    76,
                    600,
                    82
                ],
                [
                    488,
                    76,
                    600,
                    82
                ],
                [
                    488,
                    76,
                    600,
                    82
                ],
                [
                    488,
                    76,
                    600,
                    82
                ],
                [
                    605,
                    76,
                    623,
                    82
                ],
                [
                    627,
                    76,
                    728,
                    84
                ],
                [
                    627,
                    76,
                    728,
                    84
                ],
                [
                    627,
                    76,
                    728,
                    84
                ],
                [
                    627,
                    76,
                    728,
                    84
                ],
                [
                    627,
                    76,
                    728,
                    84
                ],
                [
                    627,
                    76,
                    728,
                    84
                ],
                [
                    627,
                    76,
                    728,
                    84
                ],
                [
                    104,
                    100,
                    142,
                    111
                ],
                [
                    104,
                    100,
                    142,
                    111
                ],
                [
                    104,
                    100,
                    142,
                    111
                ],
                [
                    104,
                    100,
                    142,
                    111
                ],
                [
                    104,
                    100,
                    142,
                    111
                ],
                [
                    104,
                    100,
                    142,
                    111
                ],
                [
                    104,
                    100,
                    142,
                    111
                ],
                [
                    104,
                    100,
                    142,
                    111
                ],
                [
                    246,
                    101,
                    313,
                    107
                ],
                [
                    246,
                    101,
                    313,
                    107
                ],
                [
                    246,
                    101,
                    313,
                    107
                ],
                [
                    318,
                    101,
                    410,
                    109
                ],
                [
                    318,
                    101,
                    410,
                    109
                ],
                [
                    318,
                    101,
                    410,
                    109
                ],
                [
                    318,
                    101,
                    410,
                    109
                ],
                [
                    318,
                    101,
                    410,
                    109
                ],
                [
                    415,
                    102,
                    445,
                    107
                ],
                [
                    415,
                    102,
                    445,
                    107
                ],
                [
                    450,
                    102,
                    463,
                    107
                ],
                [
                    468,
                    101,
                    525,
                    107
                ],
                [
                    468,
                    101,
                    525,
                    107
                ],
                [
                    468,
                    101,
                    525,
                    107
                ],
                [
                    529,
                    102,
                    545,
                    107
                ],
                [
                    566,
                    109,
                    571,
                    109
                ],
                [
                    589,
                    102,
                    629,
                    107
                ],
                [
                    589,
                    102,
                    629,
                    107
                ],
                [
                    589,
                    102,
                    629,
                    107
                ],
                [
                    589,
                    102,
                    629,
                    107
                ],
                [
                    633,
                    102,
                    651,
                    109
                ],
                [
                    856,
                    101,
                    913,
                    107
                ],
                [
                    856,
                    101,
                    913,
                    107
                ],
                [
                    856,
                    101,
                    913,
                    107
                ],
                [
                    856,
                    101,
                    913,
                    107
                ],
                [
                    856,
                    101,
                    913,
                    107
                ],
                [
                    246,
                    110,
                    348,
                    118
                ],
                [
                    246,
                    110,
                    348,
                    118
                ],
                [
                    246,
                    110,
                    348,
                    118
                ],
                [
                    246,
                    110,
                    348,
                    118
                ],
                [
                    246,
                    110,
                    348,
                    118
                ],
                [
                    356,
                    110,
                    371,
                    117
                ],
                [
                    378,
                    110,
                    401,
                    116
                ],
                [
                    378,
                    110,
                    401,
                    116
                ],
                [
                    407,
                    110,
                    491,
                    116
                ],
                [
                    407,
                    110,
                    491,
                    116
                ],
                [
                    407,
                    110,
                    491,
                    116
                ],
                [
                    407,
                    110,
                    491,
                    116
                ],
                [
                    407,
                    110,
                    491,
                    116
                ],
                [
                    498,
                    110,
                    514,
                    116
                ],
                [
                    521,
                    110,
                    581,
                    117
                ],
                [
                    521,
                    110,
                    581,
                    117
                ],
                [
                    521,
                    110,
                    581,
                    117
                ],
                [
                    246,
                    118,
                    298,
                    124
                ],
                [
                    246,
                    118,
                    298,
                    124
                ],
                [
                    246,
                    118,
                    298,
                    124
                ],
                [
                    304,
                    118,
                    310,
                    124
                ],
                [
                    318,
                    118,
                    370,
                    124
                ],
                [
                    318,
                    118,
                    370,
                    124
                ],
                [
                    318,
                    118,
                    370,
                    124
                ],
                [
                    376,
                    118,
                    450,
                    124
                ],
                [
                    376,
                    118,
                    450,
                    124
                ],
                [
                    376,
                    118,
                    450,
                    124
                ],
                [
                    376,
                    118,
                    450,
                    124
                ],
                [
                    0,
                    0,
                    0,
                    0
                ]
            ],
            "predicciones": [
                0,
                0,
                0,
                0,
                0,
                0,
                0,
                0,
                0,
                0,
                0,
                0,
                0,
                0,
                0,
                0,
                0,
                0,
                0,
                0,
                0,
                0,
                0,
                0,
                0,
                0,
                0,
                0,
                0,
                0,
                0,
                0,
                0,
                0,
                0,
                0,
                0,
                0,
                0,
                0,
                0,
                0,
                0,
                1,
                0,
                0,
                0,
                0,
                0,
                0,
                0,
                0,
                0,
                0,
                0,
                0,
                0,
                0,
                0,
                0,
                0,
                0,
                0,
                0,
                0,
                0,
                1,
                1,
                1,
                1,
                1,
                0,
                0,
                0,
                0,
                0,
                0,
                0,
                0,
                0,
                0,
                0,
                0,
                0,
                0,
                0,
                0,
                0,
                0,
                0,
                0,
                0,
                0,
                0,
                0,
                0,
                0,
                0,
                0,
                0
            ]
        }
    ]
}