{
    "pagina": 690,
    "segmentos": [
        {
            "tokens": [
                0,
                14159,
                139,
                1890,
                2684,
                263,
                47531,
                757,
                4843,
                366,
                29781,
                6528,
                1879,
                366,
                44,
                48,
                14740,
                5383,
                2076,
                13449,
                26747,
                7744,
                2118,
                16286,
                5885,
                41623,
                2620,
                5382,
                673,
                5885,
                226,
                2620,
                3813,
                32448,
                1864,
                9162,
                113,
                3292,
                155,
                12938,
                1423,
                27856,
                821,
                43,
                3292,
                1549,
                12938,
                10611,
                975,
                43453,
                5885,
                26933,
                4186,
                3411,
                6433,
                854,
                39995,
                2068,
                673,
                28107,
                500,
                4923,
                4629,
                1721,
                574,
                2981,
                974,
                30818,
                12112,
                73,
                698,
                73,
                37446,
                3292,
                4,
                11061,
                14830,
                1780,
                3178,
                1615,
                6304,
                5112,
                28594,
                234,
                1043,
                6073,
                263,
                29781,
                13249,
                118,
                401,
                282,
                263,
                15483,
                15953,
                4903,
                139,
                17901,
                5593,
                139,
                9000,
                242,
                234,
                12938,
                9465,
                406,
                12,
                23301,
                12,
                448,
                6078,
                4,
                291,
                73,
                3387,
                73,
                23301,
                3292,
                352,
                176,
                30644,
                9162,
                387,
                1889,
                44101,
                250,
                5885,
                24428,
                791,
                3376,
                7744,
                5885,
                28922,
                3411,
                6433,
                5885,
                1721,
                1793,
                3898,
                19209,
                4722,
                256,
                25938,
                2336,
                5885,
                26933,
                4186,
                3411,
                6433,
                221,
                3411,
                4729,
                2191,
                6390,
                221,
                3450,
                673,
                4,
                384,
                4,
                500,
                4,
                234,
                12938,
                15786,
                12,
                24789,
                272,
                4,
                500,
                4,
                226,
                2620,
                387,
                4,
                111,
                4307,
                1132,
                73,
                3933,
                73,
                24789,
                2
            ],
            "texto_original": " Texto Unico de Procedimientos Administrativos “GOBIERNO REGIONAL DEL DEPARTAMENTO DE LAMBAYEQUE\" Art 3° y literal g) Art16° LEY GENERAL DE TRANSPORTE Y TRANSITO TERRESTRE |Ley 27181 08/10/1999 Art. 105 Aprueba el Reglamento Nacional de Administraci6n de|Decreto Supremo Transporte N° 017-2009-MTC. 20/04/2009 Artly2 APRUEBAN PROGRAMA DE REDUCCION DE IMPORTE DE | Ordenanza Regional MULTAS DE TRANSPORTE POR PRONTO PAGO. O.R. N° 05-2010 G.R. LAMB. - CR 29/03/2010",
            "coordenadas": [
                [
                    0,
                    0,
                    0,
                    0
                ],
                [
                    361,
                    62,
                    396,
                    68
                ],
                [
                    361,
                    62,
                    396,
                    68
                ],
                [
                    401,
                    60,
                    437,
                    68
                ],
                [
                    401,
                    60,
                    437,
                    68
                ],
                [
                    442,
                    61,
                    456,
                    68
                ],
                [
                    462,
                    61,
                    561,
                    68
                ],
                [
                    462,
                    61,
                    561,
                    68
                ],
                [
                    462,
                    61,
                    561,
                    68
                ],
                [
                    462,
                    61,
                    561,
                    68
                ],
                [
                    566,
                    61,
                    666,
                    68
                ],
                [
                    566,
                    61,
                    666,
                    68
                ],
                [
                    566,
                    61,
                    666,
                    68
                ],
                [
                    566,
                    61,
                    666,
                    68
                ],
                [
                    300,
                    76,
                    378,
                    82
                ],
                [
                    300,
                    76,
                    378,
                    82
                ],
                [
                    300,
                    76,
                    378,
                    82
                ],
                [
                    300,
                    76,
                    378,
                    82
                ],
                [
                    300,
                    76,
                    378,
                    82
                ],
                [
                    300,
                    76,
                    378,
                    82
                ],
                [
                    382,
                    76,
                    453,
                    82
                ],
                [
                    382,
                    76,
                    453,
                    82
                ],
                [
                    382,
                    76,
                    453,
                    82
                ],
                [
                    457,
                    76,
                    483,
                    82
                ],
                [
                    488,
                    76,
                    600,
                    82
                ],
                [
                    488,
                    76,
                    600,
                    82
                ],
                [
                    488,
                    76,
                    600,
                    82
                ],
                [
                    488,
                    76,
                    600,
                    82
                ],
                [
                    488,
                    76,
                    600,
                    82
                ],
                [
                    605,
                    76,
                    623,
                    82
                ],
                [
                    627,
                    76,
                    728,
                    84
                ],
                [
                    627,
                    76,
                    728,
                    84
                ],
                [
                    627,
                    76,
                    728,
                    84
                ],
                [
                    627,
                    76,
                    728,
                    84
                ],
                [
                    627,
                    76,
                    728,
                    84
                ],
                [
                    627,
                    76,
                    728,
                    84
                ],
                [
                    627,
                    76,
                    728,
                    84
                ],
                [
                    104,
                    102,
                    119,
                    107
                ],
                [
                    122,
                    101,
                    133,
                    107
                ],
                [
                    122,
                    101,
                    133,
                    107
                ],
                [
                    132,
                    100,
                    138,
                    111
                ],
                [
                    136,
                    101,
                    173,
                    109
                ],
                [
                    177,
                    101,
                    186,
                    109
                ],
                [
                    177,
                    101,
                    186,
                    109
                ],
                [
                    190,
                    101,
                    223,
                    107
                ],
                [
                    190,
                    101,
                    223,
                    107
                ],
                [
                    190,
                    101,
                    223,
                    107
                ],
                [
                    246,
                    102,
                    266,
                    107
                ],
                [
                    246,
                    102,
                    266,
                    107
                ],
                [
                    271,
                    101,
                    326,
                    107
                ],
                [
                    331,
                    102,
                    346,
                    107
                ],
                [
                    350,
                    101,
                    430,
                    107
                ],
                [
                    350,
                    101,
                    430,
                    107
                ],
                [
                    350,
                    101,
                    430,
                    107
                ],
                [
                    350,
                    101,
                    430,
                    107
                ],
                [
                    434,
                    102,
                    441,
                    107
                ],
                [
                    445,
                    101,
                    503,
                    107
                ],
                [
                    445,
                    101,
                    503,
                    107
                ],
                [
                    445,
                    101,
                    503,
                    107
                ],
                [
                    507,
                    101,
                    578,
                    107
                ],
                [
                    507,
                    101,
                    578,
                    107
                ],
                [
                    507,
                    101,
                    578,
                    107
                ],
                [
                    507,
                    101,
                    578,
                    107
                ],
                [
                    589,
                    102,
                    606,
                    109
                ],
                [
                    589,
                    102,
                    606,
                    109
                ],
                [
                    589,
                    102,
                    606,
                    109
                ],
                [
                    761,
                    101,
                    793,
                    107
                ],
                [
                    761,
                    101,
                    793,
                    107
                ],
                [
                    855,
                    101,
                    913,
                    107
                ],
                [
                    855,
                    101,
                    913,
                    107
                ],
                [
                    855,
                    101,
                    913,
                    107
                ],
                [
                    855,
                    101,
                    913,
                    107
                ],
                [
                    855,
                    101,
                    913,
                    107
                ],
                [
                    104,
                    117,
                    121,
                    123
                ],
                [
                    104,
                    117,
                    121,
                    123
                ],
                [
                    126,
                    117,
                    145,
                    123
                ],
                [
                    245,
                    117,
                    294,
                    124
                ],
                [
                    245,
                    117,
                    294,
                    124
                ],
                [
                    245,
                    117,
                    294,
                    124
                ],
                [
                    301,
                    117,
                    310,
                    123
                ],
                [
                    318,
                    117,
                    387,
                    124
                ],
                [
                    318,
                    117,
                    387,
                    124
                ],
                [
                    318,
                    117,
                    387,
                    124
                ],
                [
                    396,
                    117,
                    445,
                    123
                ],
                [
                    396,
                    117,
                    445,
                    123
                ],
                [
                    396,
                    117,
                    445,
                    123
                ],
                [
                    453,
                    117,
                    466,
                    123
                ],
                [
                    473,
                    117,
                    560,
                    123
                ],
                [
                    473,
                    117,
                    560,
                    123
                ],
                [
                    473,
                    117,
                    560,
                    123
                ],
                [
                    473,
                    117,
                    560,
                    123
                ],
                [
                    473,
                    117,
                    560,
                    123
                ],
                [
                    568,
                    117,
                    629,
                    123
                ],
                [
                    568,
                    117,
                    629,
                    123
                ],
                [
                    568,
                    117,
                    629,
                    123
                ],
                [
                    568,
                    117,
                    629,
                    123
                ],
                [
                    568,
                    117,
                    629,
                    123
                ],
                [
                    633,
                    117,
                    679,
                    124
                ],
                [
                    633,
                    117,
                    679,
                    124
                ],
                [
                    633,
                    117,
                    679,
                    124
                ],
                [
                    245,
                    126,
                    308,
                    133
                ],
                [
                    245,
                    126,
                    308,
                    133
                ],
                [
                    730,
                    117,
                    742,
                    123
                ],
                [
                    730,
                    117,
                    742,
                    123
                ],
                [
                    746,
                    117,
                    824,
                    123
                ],
                [
                    746,
                    117,
                    824,
                    123
                ],
                [
                    746,
                    117,
                    824,
                    123
                ],
                [
                    746,
                    117,
                    824,
                    123
                ],
                [
                    746,
                    117,
                    824,
                    123
                ],
                [
                    746,
                    117,
                    824,
                    123
                ],
                [
                    746,
                    117,
                    824,
                    123
                ],
                [
                    746,
                    117,
                    824,
                    123
                ],
                [
                    856,
                    117,
                    913,
                    123
                ],
                [
                    856,
                    117,
                    913,
                    123
                ],
                [
                    856,
                    117,
                    913,
                    123
                ],
                [
                    856,
                    117,
                    913,
                    123
                ],
                [
                    856,
                    117,
                    913,
                    123
                ],
                [
                    104,
                    141,
                    147,
                    148
                ],
                [
                    104,
                    141,
                    147,
                    148
                ],
                [
                    104,
                    141,
                    147,
                    148
                ],
                [
                    245,
                    141,
                    310,
                    147
                ],
                [
                    245,
                    141,
                    310,
                    147
                ],
                [
                    245,
                    141,
                    310,
                    147
                ],
                [
                    245,
                    141,
                    310,
                    147
                ],
                [
                    316,
                    141,
                    384,
                    147
                ],
                [
                    316,
                    141,
                    384,
                    147
                ],
                [
                    390,
                    141,
                    404,
                    147
                ],
                [
                    410,
                    139,
                    480,
                    147
                ],
                [
                    410,
                    139,
                    480,
                    147
                ],
                [
                    410,
                    139,
                    480,
                    147
                ],
                [
                    410,
                    139,
                    480,
                    147
                ],
                [
                    486,
                    141,
                    502,
                    147
                ],
                [
                    507,
                    141,
                    560,
                    147
                ],
                [
                    507,
                    141,
                    560,
                    147
                ],
                [
                    507,
                    141,
                    560,
                    147
                ],
                [
                    566,
                    141,
                    580,
                    147
                ],
                [
                    575,
                    138,
                    584,
                    150
                ],
                [
                    588,
                    141,
                    646,
                    147
                ],
                [
                    588,
                    141,
                    646,
                    147
                ],
                [
                    588,
                    141,
                    646,
                    147
                ],
                [
                    650,
                    141,
                    695,
                    148
                ],
                [
                    246,
                    149,
                    293,
                    155
                ],
                [
                    246,
                    149,
                    293,
                    155
                ],
                [
                    246,
                    149,
                    293,
                    155
                ],
                [
                    298,
                    149,
                    313,
                    155
                ],
                [
                    318,
                    149,
                    399,
                    155
                ],
                [
                    318,
                    149,
                    399,
                    155
                ],
                [
                    318,
                    149,
                    399,
                    155
                ],
                [
                    318,
                    149,
                    399,
                    155
                ],
                [
                    405,
                    149,
                    429,
                    155
                ],
                [
                    405,
                    149,
                    429,
                    155
                ],
                [
                    434,
                    149,
                    484,
                    155
                ],
                [
                    434,
                    149,
                    484,
                    155
                ],
                [
                    434,
                    149,
                    484,
                    155
                ],
                [
                    490,
                    149,
                    523,
                    155
                ],
                [
                    490,
                    149,
                    523,
                    155
                ],
                [
                    490,
                    149,
                    523,
                    155
                ],
                [
                    490,
                    149,
                    523,
                    155
                ],
                [
                    721,
                    141,
                    743,
                    147
                ],
                [
                    721,
                    141,
                    743,
                    147
                ],
                [
                    721,
                    141,
                    743,
                    147
                ],
                [
                    721,
                    141,
                    743,
                    147
                ],
                [
                    748,
                    141,
                    760,
                    147
                ],
                [
                    748,
                    141,
                    760,
                    147
                ],
                [
                    764,
                    141,
                    807,
                    147
                ],
                [
                    764,
                    141,
                    807,
                    147
                ],
                [
                    764,
                    141,
                    807,
                    147
                ],
                [
                    811,
                    141,
                    833,
                    147
                ],
                [
                    811,
                    141,
                    833,
                    147
                ],
                [
                    811,
                    141,
                    833,
                    147
                ],
                [
                    811,
                    141,
                    833,
                    147
                ],
                [
                    747,
                    149,
                    780,
                    155
                ],
                [
                    747,
                    149,
                    780,
                    155
                ],
                [
                    747,
                    149,
                    780,
                    155
                ],
                [
                    747,
                    149,
                    780,
                    155
                ],
                [
                    785,
                    152,
                    788,
                    153
                ],
                [
                    792,
                    149,
                    808,
                    155
                ],
                [
                    856,
                    141,
                    913,
                    147
                ],
                [
                    856,
                    141,
                    913,
                    147
                ],
                [
                    856,
                    141,
                    913,
                    147
                ],
                [
                    856,
                    141,
                    913,
                    147
                ],
                [
                    856,
                    141,
                    913,
                    147
                ],
                [
                    0,
                    0,
                    0,
                    0
                ]
            ],
            "predicciones": [
                0,
                0,
                0,
                0,
                0,
                0,
                0,
                0,
                0,
                0,
                0,
                0,
                0,
                0,
                0,
                0,
                0,
                0,
                0,
                0,
                0,
                0,
                0,
                0,
                0,
                0,
                0,
                0,
                0,
                0,
                0,
                0,
                0,
                0,
                0,
                0,
                0,
                0,
                1,
                0,
                1,
                0,
                0,
                0,
                0,
                0,
                0,
                0,
                1,
                0,
                0,
                0,
                0,
                0,
                0,
                0,
                0,
                0,
                0,
                0,
                0,
                0,
                0,
                0,
                0,
                1,
                1,
                1,
                0,
                1,
                0,
                1,
                1,
                0,
                1,
                0,
                0,
                0,
                0,
                0,
                0,
                0,
                0,
                0,
                0,
                0,
                0,
                0,
                0,
                0,
                0,
                0,
                0,
                0,
                0,
                0,
                0,
                0,
                0,
                0,
                0,
                0,
                0,
                0,
                0,
                1,
                1,
                1,
                1,
                1,
                0,
                1,
                0,
                1,
                0,
                1,
                1,
                1,
                0,
                1,
                1,
                0,
                0,
                0,
                0,
                0,
                0,
                0,
                0,
                0,
                0,
                0,
                0,
                0,
                1,
                0,
                0,
                0,
                0,
                0,
                0,
                0,
                0,
                0,
                0,
                0,
                0,
                0,
                0,
                0,
                0,
                0,
                0,
                0,
                0,
                0,
                0,
                0,
                1,
                1,
                1,
                1,
                1,
                0,
                0,
                1,
                1,
                1,
                1,
                1,
                1,
                1,
                1,
                1,
                1,
                0,
                1,
                1,
                1,
                0,
                1,
                1,
                0
            ]
        }
    ]
}